{
    "1388701487357497464": {
        "roblox": "VoidHunter_ofc",
        "numero": 63,
        "guilda": "hades",
        "idioma": "pt",
        "dps": "80 Oc",
        "farm": "1 Oc",
        "rank": "GM",
        "level": 167,
        "tempo": "69 dias",
        "data": "03/07/2025",
        "discord": "1388701487357497464"
    },
    "521096158324457502": {
        "roblox": "Deadpool503020",
        "numero": 64,
        "guilda": "hades",
        "idioma": "pt",
        "dps": "480 oc",
        "farm": "1,5 oc",
        "rank": "gm+",
        "level": 235,
        "tempo": "40 dias",
        "data": "04/07/2025",
        "discord": "521096158324457502"
    },
    "668903556190830676": {
        "roblox": "fernandoliki25",
        "numero": 65,
        "guilda": "hades",
        "idioma": "pt",
        "dps": "35Oc",
        "farm": "1 Oc",
        "rank": "GM+",
        "level": 241,
        "tempo": "17:19:03",
        "data": "05/07/2025",
        "discord": "668903556190830676"
   },
   "654091727837069368": {
        "roblox": "Z0rdy3",
        "numero": 66,
        "guilda": "hades",
        "idioma": "pt",
        "dps": "300 Oc",
        "farm": "10-30 Oc",
        "rank": "GM+",
        "level": 215,
        "tempo": "16 dias",
        "data": "05/07/2025",
        "discord": "654091727837069368"
    },
    "882719168594587669": {
        "roblox": "S4TOR0_GOJ0",
        "numero": 67,
        "guilda": "hades",
        "idioma": "pt",
        "dps": "480Oc",
        "farm": "1.0Oc - 1.5Oc",
        "rank": "GM+",
        "level": 231,
        "tempo": "5 DIAS",
        "data": "04/07/2025",
        "discord": "882719168594587669"
    },
    "998029078923853834": {
        "roblox": "YokisobaG",
        "numero": 68,
        "guilda": "hades",
        "idioma": "pt",
        "dps": "2.12No",
        "farm": "10.04Oc",
        "rank": "gm+",
        "level": 300,
        "tempo": "24 dias",
        "data": "04/07/2025",
        "discord": "998029078923853834"
    },
    "1254710832101589062": {
        "roblox": "kskjks12321",
        "numero": 69,
        "guilda": "hades",
        "idioma": "pt",
        "dps": "900Oc",
        "farm": "50Oc",
        "rank": "GM+",
        "level": 250,
        "tempo": "8 dias e 14 horas",
        "data": "04/07/2025",
        "discord": "1254710832101589062"
    },
    "431126859254595595": {
        "roblox": "AncestralGod",
        "numero": 70,
        "guilda": "hades",
        "idioma": "pt",
        "dps": "250Oc",
        "farm": "5Oc",
        "rank": "GM+",
        "level": 213,
        "tempo": "3 dias e 18 hrs",
        "data": "04/07/2025",
        "discord": "431126859254595595"
    },
    "763378677978759169": {
        "roblox": "boom_craftpro",
        "numero": 71,
        "guilda": "hades",
        "idioma": "pt",
        "dps": "1No",
        "farm": "2 oc",
        "rank": "Gm+",
        "level": 209,
        "tempo": "23d",
        "data": "04/07/2025",
        "discord": "763378677978759169"
    },
    "763728376715804683": {
        "roblox": "xxby_dragon",
        "numero": 72,
        "guilda": "hades",
        "idioma": "pt",
        "dps": "105Oc",
        "farm": "20Oc",
        "rank": "GM+",
        "level": 235,
        "tempo": "8 Dias",
        "data": "04/07/2025",
        "discord": "763728376715804683"
    },
    "1323132489308442628": {
        "roblox": "aAA9998j",
        "numero": 73,
        "guilda": "hades",
        "idioma": "pt",
        "dps": "850 Oc",
        "farm": "50-150 Oc",
        "rank": "GM+",
        "level": 285,
        "tempo": "36 Dias",
        "data": "04/06/2025",
        "discord": "1323132489308442628"
    },
    "888470146790858782": {
        "roblox": "grozadoido",
        "numero": 74,
        "guilda": "hades",
        "idioma": "pt",
        "dps": "3,50N",
        "farm": "20C",
        "rank": "GM+",
        "level": 242,
        "tempo": "31dias",
        "data": "04/07/2025",
        "discord": "888470146790858782"
    },
    "1075560772937199687": {
        "roblox": "Testudo12345678919",
        "numero": 75,
        "guilda": "hades",
        "idioma": "pt",
        "dps": "115 Oc",
        "farm": "4-8oc",
        "rank": "GM+",
        "level": 230,
        "tempo": "9 dias",
        "data": "04/07/2025",
        "discord": "1075560772937199687"
    },
    "1011074058059780106": {
        "roblox": "Black_Bird",
        "numero": 76,
        "guilda": "hades",
        "idioma": "pt",
        "dps": "638Oc",
        "farm": "80Oc",
        "rank": "GM+",
        "level": 288,
        "tempo": "12 hrs mais ou menos",
        "data": "06/07/2025",
        "discord": "1011074058059780106"
     },
    "826208609620197406": {
        "roblox": "eo_sak1",
        "numero": 77,
        "guilda": "Hades",
        "idioma": "pt",
        "dps": "19no",
        "farm": "1000oc",
        "rank": "GM+",
        "level": 277,
        "tempo": "37 dias",
        "data": "07/07/2025",
        "discord": "826208609620197406"
    },
    "1361414003208753392": {
        "roblox": "scorpionzinho_br",
         "numero": 78,
         "guilda": "Hades",
         "idioma": "pt",
         "dps": "14No",
         "farm": "50–1000c",
         "rank": "GM+",
         "level": 320,
         "tempo": "55 dias",
         "data": "07/07/2025",
         "discord": "1361414003208753392"
      },
    "904210158094286899": {
         "roblox": "FelipEcr72",
         "numero": 79,
         "guilda": "Hades",
         "idioma": "pt",
         "dps": "130No",
         "farm": "1000c",
         "rank": "GM+",
         "level": 326,
         "tempo": "7hrs",
         "data": "07/07/2025",
         "discord": "904210158094286899"
     },
    "1320448759880224789": {
         "roblox": "EMRGM7",
         "numero": 80,
         "guilda": "Hades",
         "idioma": "pt",
         "dps": "102No",
         "farm": "100oc",
         "rank": "GM+",
         "level": 326,
         "tempo": "23 dias",
         "data": "08/07/2025",
         "discord": "1320448759880224789"
    },
    "318464726122102784": {
        "roblox": "Formigao",
        "numero": 81,
        "guilda": "Hades",
        "idioma": "pt",
        "dps": "91 no",
        "farm": "200Oc",
        "rank": "GM+",
        "level": 307,
        "tempo": "58 dias",
        "data": "08/07/2025",
        "discord": "318464726122102784"
     },
    "231914234974437377": {
        "roblox": "Hegy123",
        "numero": 82,
        "guilda": "hades",
        "idioma": "pt",
        "dps": "150 No",
        "farm": "250 Oc",
        "rank": "GM+",
        "level": 310,
        "tempo": "45 Dias",
        "data": "08/07/2025",
        "discord": "231914234974437377"
    },
   "1090398682182074471": {
        "numero": 96,
        "guilda": "Hades",
        "roblox": "Ytthhghhgfggffffds",
        "discord": "1090398682182074471",
        "data": "08/07/2025"
   }
}

